odoo/addons/ssi_revenue_recognition_work_log/README.rst
odoo/addons/ssi_revenue_recognition_work_log/__init__.py
odoo/addons/ssi_revenue_recognition_work_log/__manifest__.py
odoo/addons/ssi_revenue_recognition_work_log/models/__init__.py
odoo/addons/ssi_revenue_recognition_work_log/models/performance_obligation_acceptance.py
odoo/addons/ssi_revenue_recognition_work_log/models/revenue_recognition.py
odoo/addons/ssi_revenue_recognition_work_log/models/service_contract_performance_obligation.py
odoo/addons/ssi_revenue_recognition_work_log/static/description/icon.png
odoo/addons/ssi_revenue_recognition_work_log/views/performance_obligation_acceptance_views.xml
odoo14_addon_ssi_revenue_recognition_work_log-14.0.1.2.0.dist-info/METADATA
odoo14_addon_ssi_revenue_recognition_work_log-14.0.1.2.0.dist-info/WHEEL
odoo14_addon_ssi_revenue_recognition_work_log-14.0.1.2.0.dist-info/top_level.txt
odoo14_addon_ssi_revenue_recognition_work_log-14.0.1.2.0.dist-info/RECORD
